magicweb/__init__.py
magicweb/routes.py
Magicweb-2.0.3.dist-info/LICENSE
Magicweb-2.0.3.dist-info/METADATA
Magicweb-2.0.3.dist-info/WHEEL
Magicweb-2.0.3.dist-info/top_level.txt
Magicweb-2.0.3.dist-info/RECORD
