Metadata-Version: 2.1
Name: Magicweb
Version: 2.0.3
Summary: A simple web framework
Home-page: https://github.com/mordy-python/magicweb
Author: Israel Waldner
Author-email: imky171@gmail.com
License: MIT
Download-URL: https://pypi.org/project/magicweb/
Keywords: Web,Web framework,framework
Platform: UNKNOWN
License-File: LICENSE
Requires-Dist: parse
Requires-Dist: webob
Requires-Dist: waitress
Requires-Dist: jinja2
